etta/__init__.py
etta/helpers.py
etta/php_wrappers.py
etta/sanity.py
etta/test.py
etta-0.1.1.dist-info/LICENSE
etta-0.1.1.dist-info/METADATA
etta-0.1.1.dist-info/WHEEL
etta-0.1.1.dist-info/top_level.txt
etta-0.1.1.dist-info/RECORD
